{"name":"build-javascript","namedChunkGroups":{"app":{"name":"app","assets":[{"name":"webpack-runtime-9c9cae0bb7803ca7a894.js","size":4433},{"name":"framework-6cbec7abefab452d7ac3.js","size":210887},{"name":"styles.075c643daff16e53243b.css","size":239071},{"name":"app-f356655c1f638c3bcad6.js","size":177450}],"filteredAssets":0,"assetsSize":631841,"filteredAuxiliaryAssets":3,"auxiliaryAssetsSize":1133023},"component---src-pages-404-js":{"name":"component---src-pages-404-js","assets":[{"name":"framework-6cbec7abefab452d7ac3.js","size":210887},{"name":"styles.075c643daff16e53243b.css","size":239071},{"name":"2cca2479-deb68bc3b653a28a6408.js","size":3402},{"name":"commons-5c8f8d8dd2c97dc74f22.js","size":154711},{"name":"component---src-pages-404-js-df3cbb3acc16e6f27aba.js","size":1364}],"filteredAssets":0,"assetsSize":609435,"filteredAuxiliaryAssets":4,"auxiliaryAssetsSize":1429984},"component---src-pages-authors-js":{"name":"component---src-pages-authors-js","assets":[{"name":"framework-6cbec7abefab452d7ac3.js","size":210887},{"name":"styles.075c643daff16e53243b.css","size":239071},{"name":"2cca2479-deb68bc3b653a28a6408.js","size":3402},{"name":"commons-5c8f8d8dd2c97dc74f22.js","size":154711},{"name":"5ef75968fba327e6e4f74fc7f3d97740cf391abf-686553fd952e1c0442b3.js","size":8922},{"name":"component---src-pages-authors-js-8f5560a31b25ff26be1e.js","size":1222}],"filteredAssets":0,"assetsSize":618215,"filteredAuxiliaryAssets":5,"auxiliaryAssetsSize":1473430},"component---src-pages-tags-js":{"name":"component---src-pages-tags-js","assets":[{"name":"framework-6cbec7abefab452d7ac3.js","size":210887},{"name":"styles.075c643daff16e53243b.css","size":239071},{"name":"2cca2479-deb68bc3b653a28a6408.js","size":3402},{"name":"commons-5c8f8d8dd2c97dc74f22.js","size":154711},{"name":"5ef75968fba327e6e4f74fc7f3d97740cf391abf-686553fd952e1c0442b3.js","size":8922},{"name":"component---src-pages-tags-js-d4aabacdb73d25c69c37.js","size":1203}],"filteredAssets":0,"assetsSize":618196,"filteredAuxiliaryAssets":5,"auxiliaryAssetsSize":1473378},"component---src-templates-authors-js":{"name":"component---src-templates-authors-js","assets":[{"name":"framework-6cbec7abefab452d7ac3.js","size":210887},{"name":"styles.075c643daff16e53243b.css","size":239071},{"name":"2cca2479-deb68bc3b653a28a6408.js","size":3402},{"name":"commons-5c8f8d8dd2c97dc74f22.js","size":154711},{"name":"5ef75968fba327e6e4f74fc7f3d97740cf391abf-686553fd952e1c0442b3.js","size":8922},{"name":"component---src-templates-authors-js-6949cab83302b677f217.js","size":5705}],"filteredAssets":0,"assetsSize":622698,"filteredAuxiliaryAssets":5,"auxiliaryAssetsSize":1483979},"component---src-templates-blog-page-js":{"name":"component---src-templates-blog-page-js","assets":[{"name":"framework-6cbec7abefab452d7ac3.js","size":210887},{"name":"styles.075c643daff16e53243b.css","size":239071},{"name":"2cca2479-deb68bc3b653a28a6408.js","size":3402},{"name":"commons-5c8f8d8dd2c97dc74f22.js","size":154711},{"name":"5ef75968fba327e6e4f74fc7f3d97740cf391abf-686553fd952e1c0442b3.js","size":8922},{"name":"component---src-templates-blog-page-js-13b8a9a5a96a3d402ad4.js","size":2037}],"filteredAssets":0,"assetsSize":619030,"filteredAuxiliaryAssets":5,"auxiliaryAssetsSize":1476910},"component---src-templates-index-js":{"name":"component---src-templates-index-js","assets":[{"name":"framework-6cbec7abefab452d7ac3.js","size":210887},{"name":"styles.075c643daff16e53243b.css","size":239071},{"name":"2cca2479-deb68bc3b653a28a6408.js","size":3402},{"name":"commons-5c8f8d8dd2c97dc74f22.js","size":154711},{"name":"component---src-templates-index-js-1b63064e189049183913.js","size":8065}],"filteredAssets":0,"assetsSize":616136,"filteredAuxiliaryAssets":4,"auxiliaryAssetsSize":1447127},"component---src-templates-page-js":{"name":"component---src-templates-page-js","assets":[{"name":"framework-6cbec7abefab452d7ac3.js","size":210887},{"name":"styles.075c643daff16e53243b.css","size":239071},{"name":"2cca2479-deb68bc3b653a28a6408.js","size":3402},{"name":"commons-5c8f8d8dd2c97dc74f22.js","size":154711},{"name":"component---src-templates-page-js-50b65402656f456d68be.js","size":2709}],"filteredAssets":0,"assetsSize":610780,"filteredAuxiliaryAssets":4,"auxiliaryAssetsSize":1433419},"component---src-templates-tags-js":{"name":"component---src-templates-tags-js","assets":[{"name":"framework-6cbec7abefab452d7ac3.js","size":210887},{"name":"styles.075c643daff16e53243b.css","size":239071},{"name":"2cca2479-deb68bc3b653a28a6408.js","size":3402},{"name":"commons-5c8f8d8dd2c97dc74f22.js","size":154711},{"name":"5ef75968fba327e6e4f74fc7f3d97740cf391abf-686553fd952e1c0442b3.js","size":8922},{"name":"component---src-templates-tags-js-2a2342096d3b4622b0a0.js","size":5695}],"filteredAssets":0,"assetsSize":622688,"filteredAuxiliaryAssets":5,"auxiliaryAssetsSize":1483995}},"assetsByChunkName":{"app":["webpack-runtime-9c9cae0bb7803ca7a894.js","framework-6cbec7abefab452d7ac3.js","styles.075c643daff16e53243b.css","app-f356655c1f638c3bcad6.js"],"component---src-pages-404-js":["framework-6cbec7abefab452d7ac3.js","styles.075c643daff16e53243b.css","2cca2479-deb68bc3b653a28a6408.js","commons-5c8f8d8dd2c97dc74f22.js","component---src-pages-404-js-df3cbb3acc16e6f27aba.js"],"component---src-pages-authors-js":["framework-6cbec7abefab452d7ac3.js","styles.075c643daff16e53243b.css","2cca2479-deb68bc3b653a28a6408.js","commons-5c8f8d8dd2c97dc74f22.js","5ef75968fba327e6e4f74fc7f3d97740cf391abf-686553fd952e1c0442b3.js","component---src-pages-authors-js-8f5560a31b25ff26be1e.js"],"component---src-pages-tags-js":["framework-6cbec7abefab452d7ac3.js","styles.075c643daff16e53243b.css","2cca2479-deb68bc3b653a28a6408.js","commons-5c8f8d8dd2c97dc74f22.js","5ef75968fba327e6e4f74fc7f3d97740cf391abf-686553fd952e1c0442b3.js","component---src-pages-tags-js-d4aabacdb73d25c69c37.js"],"component---src-templates-authors-js":["framework-6cbec7abefab452d7ac3.js","styles.075c643daff16e53243b.css","2cca2479-deb68bc3b653a28a6408.js","commons-5c8f8d8dd2c97dc74f22.js","5ef75968fba327e6e4f74fc7f3d97740cf391abf-686553fd952e1c0442b3.js","component---src-templates-authors-js-6949cab83302b677f217.js"],"component---src-templates-blog-page-js":["framework-6cbec7abefab452d7ac3.js","styles.075c643daff16e53243b.css","2cca2479-deb68bc3b653a28a6408.js","commons-5c8f8d8dd2c97dc74f22.js","5ef75968fba327e6e4f74fc7f3d97740cf391abf-686553fd952e1c0442b3.js","component---src-templates-blog-page-js-13b8a9a5a96a3d402ad4.js"],"component---src-templates-index-js":["framework-6cbec7abefab452d7ac3.js","styles.075c643daff16e53243b.css","2cca2479-deb68bc3b653a28a6408.js","commons-5c8f8d8dd2c97dc74f22.js","component---src-templates-index-js-1b63064e189049183913.js"],"component---src-templates-page-js":["framework-6cbec7abefab452d7ac3.js","styles.075c643daff16e53243b.css","2cca2479-deb68bc3b653a28a6408.js","commons-5c8f8d8dd2c97dc74f22.js","component---src-templates-page-js-50b65402656f456d68be.js"],"component---src-templates-tags-js":["framework-6cbec7abefab452d7ac3.js","styles.075c643daff16e53243b.css","2cca2479-deb68bc3b653a28a6408.js","commons-5c8f8d8dd2c97dc74f22.js","5ef75968fba327e6e4f74fc7f3d97740cf391abf-686553fd952e1c0442b3.js","component---src-templates-tags-js-2a2342096d3b4622b0a0.js"]},"childAssetsByChunkName":{}}